CHANGES.txt
LICENSE.txt
MANIFEST.in
README.rst
cprofilev.py
setup.py
CProfileV.egg-info/PKG-INFO
CProfileV.egg-info/SOURCES.txt
CProfileV.egg-info/dependency_links.txt
CProfileV.egg-info/entry_points.txt
CProfileV.egg-info/requires.txt
CProfileV.egg-info/top_level.txt